README.md
setup.py
taco_bell_python.egg-info/PKG-INFO
taco_bell_python.egg-info/SOURCES.txt
taco_bell_python.egg-info/dependency_links.txt
taco_bell_python.egg-info/requires.txt
taco_bell_python.egg-info/top_level.txt
tacobell/__init__.py
tacobell/tacobell.py