Metadata-Version: 2.1
Name: taco-bell-python
Version: 0.1.2
Summary: Order Taco Bell using Python!
Home-page: https://github.com/rssnyder/taco-bell-python
Author: Riley Snyder
Author-email: rileysndr@gmail.com
License: MIT
Platform: UNKNOWN
Classifier: License :: OSI Approved :: MIT License
Classifier: Programming Language :: Python :: 3
Classifier: Programming Language :: Python :: 3.8
